torch_xla2/CONTRIBUTING.md
torch_xla2/__init__.py
torch_xla2/config.py
torch_xla2/decompositions.py
torch_xla2/device_module.py
torch_xla2/distributed.py
torch_xla2/environment.py
torch_xla2/export.py
torch_xla2/interop.py
torch_xla2/tensor.py
torch_xla2/tf_integration.py
torch_xla2/types.py
torch_xla2/ops/__init__.py
torch_xla2/ops/jaten.py
torch_xla2/ops/jax_reimplement.py
torch_xla2/ops/jc10d.py
torch_xla2/ops/jlibrary.py
torch_xla2/ops/jtorch.py
torch_xla2/ops/jtorchvision_nms.py
torch_xla2/ops/mappings.py
torch_xla2/ops/op_base.py
torch_xla2/ops/ops_registry.py
torch_xla2-0.0.1.dev202412041639.dist-info/METADATA
torch_xla2-0.0.1.dev202412041639.dist-info/WHEEL
torch_xla2-0.0.1.dev202412041639.dist-info/licenses/LICENSE
torch_xla2-0.0.1.dev202412041639.dist-info/RECORD
