Metadata-Version: 2.3
Name: torch_xla2
Version: 0.0.1.dev202412041639
License: BSD 3-Clause License
License-File: LICENSE
Requires-Python: >=3.9
Requires-Dist: absl-py
Requires-Dist: immutabledict
Requires-Dist: pytest
Requires-Dist: torch>=2.3.0
Provides-Extra: cpu
Requires-Dist: jax[cpu]; extra == 'cpu'
Requires-Dist: jax[cpu]>=0.4.30; extra == 'cpu'
Requires-Dist: tensorflow-cpu; extra == 'cpu'
Provides-Extra: cuda
Requires-Dist: jax[cpu]>=0.4.30; extra == 'cuda'
Requires-Dist: jax[cuda12]; extra == 'cuda'
Requires-Dist: tensorflow-cpu; extra == 'cuda'
Provides-Extra: odml
Requires-Dist: jax[cpu]; extra == 'odml'
Requires-Dist: jax[cpu]>=0.4.30; extra == 'odml'
Provides-Extra: tpu
Requires-Dist: jax[cpu]>=0.4.30; extra == 'tpu'
Requires-Dist: jax[tpu]; extra == 'tpu'
Requires-Dist: tensorflow-cpu; extra == 'tpu'
